langcodes/__init__.py
langcodes/build_data.py
langcodes/data_dicts.py
langcodes/language_distance.py
langcodes/language_lists.py
langcodes/py.typed
langcodes/registry_parser.py
langcodes/tag_parser.py
langcodes/util.py
langcodes/data/language-subtag-registry.txt
langcodes/tests/README.md
langcodes/tests/test_alpha3.py
langcodes/tests/test_language.py
langcodes/tests/test_language_data.py
langcodes/tests/test_wikt_languages.py
langcodes-3.4.1.dist-info/LICENSE.txt
langcodes-3.4.1.dist-info/METADATA
langcodes-3.4.1.dist-info/WHEEL
langcodes-3.4.1.dist-info/top_level.txt
langcodes-3.4.1.dist-info/RECORD
