Metadata-Version: 2.1
Name: langcodes
Version: 3.4.1
Summary: Tools for labeling human languages with IETF language tags
Author-email: Elia Robyn Speer <rspeer@arborelia.net>
Maintainer-email: Georg Krause <mail@georg-krause.net>
Project-URL: Homepage, https://github.com/georgkrause/langcodes
Project-URL: Repository, https://github.com/georgkrause/langcodes
Project-URL: Issues, https://github.com/georgkrause/langcodes/issues
Classifier: Development Status :: 5 - Production/Stable
Classifier: License :: OSI Approved :: MIT License
Classifier: Programming Language :: Python :: 3
Classifier: Programming Language :: Python :: 3.8
Classifier: Programming Language :: Python :: 3.9
Classifier: Programming Language :: Python :: 3.10
Classifier: Programming Language :: Python :: 3.11
Classifier: Programming Language :: Python :: 3.12
Requires-Python: >=3.8
License-File: LICENSE.txt
Requires-Dist: language-data>=1.2
Provides-Extra: test
Requires-Dist: pytest; extra == "test"
Requires-Dist: pytest-cov; extra == "test"
Provides-Extra: build
Requires-Dist: build; extra == "build"
Requires-Dist: twine; extra == "build"
